{
  "English": {
    "block_Tri_LED": "Tri-LED (Slot 1) R (Slot 2) % G (Slot 3) % B (Slot 4) %",
    "port": "Port",
    "block_LED": "LED (Slot 1) (Slot 2) %",
    "block_Position_Servo": "Position Servo (Slot 1) (Slot 2) °",
    "block_Rotation_Servo": "Rotation Servo (Slot 1) (Slot 2) %",
    "block_Play_Note": "Play Note (Slot 1) for (Slot 2) Beats",
    "block_Light": "Light (Slot 1)",
    "block_Distance": "Distance (Slot 1)",
    "block_Dial": "Dial (Slot 1)",
    "block_Other": "Other (Slot 1)",
    "Accelerometer": "Accelerometer",
    "Magnetometer": "Magnetometer",
    "block_LED_Display": "Display",
    "block_Print": "Print (Slot 1 = Hello)",
    "block_Button": "Button (Slot 1)",
    "Screen_Up": "Screen Up",
    "Screen_Down": "Screen Down",
    "Tilt_Left": "Tilt Left",
    "Tilt_Right": "Tilt Right",
    "Logo_Up": "Logo Up",
    "Logo_Down": "Logo Down",
    "Shake": "Shake",
    "block_Compass": "Compass",
    "": ""
  },
  "German Translation": {
    "block_Tri_LED": "Dreifarben-LED (Slot 1) R (Slot 2) % G (Slot 3) % B (Slot 4) %",
    "port": "Anschluss",
    "block_LED": "LED (Slot 1) (Slot2) %",
    "block_Position_Servo": "Position Servo (Slot 1) (Slot 2) °",
    "block_Rotation_Servo": "Drehung Servo (Slot 1) (Slot 2) %",
    "block_Play_Note": "Spiele Note (Slot 1) für (Slot 2) Schläge",
    "block_Light": "Licht",
    "block_Distance": "Entfernung (Slot 1)",
    "block_Dial": "Drehknopf (Slot 1)",
    "block_Other": "Sonstige",
    "Accelerometer": "Beschleunigungssensor",
    "Magnetometer": "Magnetsensor",
    "block_LED_Display": "LED Anzeige",
    "block_Print": "Drucke (Slot 1 = HALLO)",
    "block_Button": "Knopf (Slot 1)",
    "Screen_Up": "Anzeige Oben",
    "Screen_Down": "Anzeige Unten",
    "Tilt_Left": "Neigung Links",
    "Tilt_Right": "Neigung Rechts",
    "Logo_Up": "Logo Oben",
    "Logo_Down": "Logo Unten",
    "Shake": "Schütteln",
    "block_Compass": "Kompass",
    "": ""
  },
  "Portuguese Translation": {
    "block_Tri_LED": "LED Tricolor (Slot 1) R (Slot 2) % G (Slot 3) % B (Slot 4) %",
    "port": "Porta",
    "block_LED": "LED (Slot 1) (Slot 2) %",
    "block_Position_Servo": "Posição do Servo (Slot 1) (Slot 2) °",
    "block_Rotation_Servo": "Rotação do Servo (Slot 1) (Slot 2) %",
    "block_Play_Note": "Toque Notas (Slot1) por (Slot2) Batidas",
    "block_Light": "Luz (Slot 1)",
    "block_Distance": "Distância (Slot 1)",
    "block_Dial": "Discar (Slot 1)",
    "block_Other": "Outro (Slot 1)",
    "Accelerometer": "Acelerômetro",
    "Magnetometer": "Magnetômetro",
    "block_LED_Display": "Visor",
    "block_Print": "Imprimir (Slot 1 = Olá)",
    "block_Button": "Tecla (Slot 1)",
    "Screen_Up": "Tela para cima",
    "Screen_Down": "Tela para baixo",
    "Tilt_Left": "Incline para a esquerda",
    "Tilt_Right": "Incline para a direita",
    "Logo_Up": "Logo para cima",
    "Logo_Down": "Logo para baixo",
    "Shake": "Agitar",
    "block_Compass": "Bússola",
    "": ""
  },
  "French Translation": {
    "block_Tri_LED": "Tri-LED (Slot 1) R (Slot 2) % G (Slot 3) % B (Slot 4) %",
    "port": "Connecteur",
    "block_LED": "LED (Slot 1) (Slot 2) %",
    "block_Position_Servo": "Position Servo (Slot 1) (Slot 2) °",
    "block_Rotation_Servo": "Rotation Servo (Slot 1) (Slot 2) %",
    "block_Play_Note": "Jouer la note (Slot 1) pour (Slot 2) battement(s)",
    "block_Light": "Lumière",
    "block_Distance": "Distance",
    "block_Dial": "Cadran",
    "block_Other": "Autre",
    "Accelerometer": "Accéléromètre",
    "Magnetometer": "Magnétomètre",
    "block_LED_Display": "Display",
    "block_Print": "Imprimer (Slot 1 = Bonjour)",
    "block_Button": "Bouton (Slot 1)",
    "Screen_Up": "Écran vers le haut",
    "Screen_Down": "Écran vers le bas",
    "Tilt_Left": "Incliner à gauche",
    "Tilt_Right": "Incliner à droite",
    "Logo_Up": "Logo vers le haut",
    "Logo_Down": "Logo vers le bas",
    "Shake": "Secouer",
    "block_Compass": "Compas",
    "": ""
  },
  "Dutch Translation": {
    "block_Tri_LED": "Tri-LED (Slot 1) R (Slot 2) % G (Slot 3) % B (Slot 4) %",
    "port": "Poort",
    "block_LED": "LED (Slot 1) (Slot 2) %",
    "block_Position_Servo": "Positie-Servo (Slot 1) (Slot 2) °",
    "block_Rotation_Servo": "Draai-Servo (Slot 1) (Slot 2) %",
    "block_Play_Note": "Speel Noot (Slot 1) voor (Slot 2) Beats",
    "block_Light": "Licht (Slot 1)",
    "block_Distance": "Afstand (Slot 1)",
    "block_Dial": "Draaiknop (Slot 1)",
    "block_Other": "Ander (Slot 1)",
    "Accelerometer": "Accelerometer",
    "Magnetometer": "Magnetometer",
    "block_LED_Display": "Scherm",
    "block_Print": "Schrijf (Slot 1 = Hello)",
    "block_Button": "Knop (Slot 1)",
    "Screen_Up": "Scherm Omhoog",
    "Screen_Down": "Scherm Omlaag",
    "Tilt_Left": "Naar Links Kantelen",
    "Tilt_Right": "Naar Rechts Kantelen",
    "Logo_Up": "Logo Omhoog",
    "Logo_Down": "Logo Omlaag",
    "Shake": "Schudden",
    "block_Compass": "Kompas",
    "": ""
  },
  "Simplified Chinese Translation": {
    "block_Tri_LED": "%u4E09%u8272LED (Slot 1) %u7EA2 (Slot 2) % %u7EFF (Slot 3) % %u84DD (Slot 4) %",
    "port": "%u7AEF",
    "block_LED": "LED (Slot 1) (Slot 2) %",
    "block_Position_Servo": "%u4F4D%u7F6E%u4F3A%u670D (Slot 1) (Slot 2) °",
    "block_Rotation_Servo": "%u65CB%u8F6C%u4F3A%u670D (Slot 1) (Slot 2) %",
    "block_Play_Note": "%u6F14%u594F %u97F3%u9636 (Slot 1)%u4E8E(Slot 2) %u62CD",
    "block_Light": "%u706F%u5149 (Slot 1)",
    "block_Distance": "%u8DDD%u79BB (Slot 1)",
    "block_Dial": "%u62E8%u53F7 (Slot 1)",
    "block_Other": "%u5176%u4ED6 (Slot 1)",
    "Accelerometer": "%u52A0%u901F%u8BA1",
    "Magnetometer": "%u78C1%u529B%u4EEA",
    "block_LED_Display": "%u663E%u793A",
    "block_Print": "%u6253%u5370 (Slot 1 = %u4F60%u597D)",
    "block_Button": "%u6309%u94AE (Slot 1)",
    "Screen_Up": "%u6B63%u9762%u671D%u4E0A",
    "Screen_Down": "%u80CC%u9762%u671D%u4E0A",
    "Tilt_Left": "%u5411%u5DE6%u503E%u659C",
    "Tilt_Right": "%u5411%u53F3%u503E%u659C",
    "Logo_Up": "%u4E0B%u5219%u504F%u4F4E",
    "Logo_Down": "%u4E0A%u5219%u504F%u4F4E",
    "Shake": "%u6643%u52A8",
    "block_Compass": "%u6307%u5357%u9488",
    "": ""
  },
  "Traditional Chinese Translation": {
    "block_Tri_LED": "%u4E09%u8272LED (Slot 1) %u7D05 (Slot 2) % %u7DA0 (Slot 3) % %u85CD (Slot 4) %",
    "port": "%u7AEF",
    "block_LED": "LED (Slot 1) (Slot 2) %",
    "block_Position_Servo": "%u4F4D%u7F6E%u4F3A%u670D (Slot 1) (Slot 2) °",
    "block_Rotation_Servo": "%u65CB%u8F49%u4F3A%u670D (Slot 1) (Slot 2) %",
    "block_Play_Note": "%u6F14%u594F %u97F3%u968E (Slot 1)%u65BC(Slot 2) %u62CD",
    "block_Light": "%u71C8%u5149 (Slot 1)",
    "block_Distance": "%u8DDD%u96E2 (Slot 1)",
    "block_Dial": "%u64A5%u865F (Slot 1)",
    "block_Other": "%u5176%u4ED6 (Slot 1)",
    "Accelerometer": "%u52A0%u901F%u8A08",
    "Magnetometer": "%u78C1%u529B%u5100",
    "block_LED_Display": "%u986F%u793A",
    "block_Print": "%u6253%u5370 (Slot 1 = %u4F60%u597D)",
    "block_Button": "%u6309%u9215 (Slot 1)",
    "Screen_Up": "%u6B63%u9762%u671D%u4E0A",
    "Screen_Down": "%u80CC%u9762%u671D%u4E0A",
    "Tilt_Left": "%u5411%u5DE6%u50BE%u659C",
    "Tilt_Right": "%u5411%u53F3%u50BE%u659C",
    "Logo_Up": "%u4E0B%u5247%u504F%u4F4E",
    "Logo_Down": "%u4E0A%u5247%u504F%u4F4E",
    "Shake": "%u6643%u52D5",
    "block_Compass": "%u6307%u5357%u91DD",
    "": ""
  },
  "Arabic Translation": {
    "block_Tri_LED": "%u0636%u0648%u0621 %u0627%u0644%u0635%u0645%u0627%u0645 %u0627%u0644%u062B%u0644%u0627%u062B%u064A %u0641%u062A%u062D%u0629 1 %u0641%u062A%u062D%u0629 2",
    "port": "",
    "block_LED": "%u0636%u0648%u0621 %u0641%u062A%u062D%u0629 1 %u0641%u062A%u062D%u0629 2",
    "block_Position_Servo": "%u0645%u0648%u0642%u0641 %u0645%u062D%u0631%u0643 %u0633%u064A%u0631%u0641%u0648 %u0627%u0644%u0645%u0624%u0627%u0632%u0631  %u0641%u062A%u062D%u0629 1 %u0641%u062A%u062D%u0629 2",
    "block_Rotation_Servo": "%u0641%u062A%u062D%u0629 %u062F%u0648%u0631%u0627%u0646 %u0627%u0644%u0645%u062D%u0631%u0643 %u0627%u0644%u0645%u0624%u0627%u0632%u0631  %u0641%u062A%u062D%u0629 1  %u0641%u062A%u062D%u0629 2",
    "block_Play_Note": "%u062A%u0634%u063A%u064A%u0644 %u0627%u0644%u0645%u0648%u0633%u064A%u0642%u0649  %u0641%u062A%u062D%u0629 1 %u0641%u062A%u062D%u0629 2",
    "block_Light": "%u0636%u0648%u0621   %u0641%u062A%u062D%u0629 1",
    "block_Distance": "%u0645%u0633%u0627%u0641%u0647   %u0641%u062A%u062D%u0629 1",
    "block_Dial": "%u062F%u0648%u0627%u0631   %u0641%u062A%u062D%u0629 1",
    "block_Other": "%u0623%u062E%u0631%u0649  %u0641%u062A%u062D%u0629 1",
    "Accelerometer": "%u0627%u0644%u062A%u0633%u0627%u0631%u0639",
    "Magnetometer": "%u0645%u0642%u064A%u0627%u0633 %u0627%u0644%u0645%u063A%u0646%u0637%u064A%u0633%u064A%u0629",
    "block_LED_Display": "%u0639%u0631%u0636",
    "block_Print": "%u0637%u0628%u0627%u0639%u0629 (%u0627%u0644%u0641%u062A%u062D%u0629 1 = %u0645%u0631%u062D%u0628%u064B%u0627)",
    "block_Button": "%u0632%u0631 (%u0641%u062A%u062D%u0629 1)",
    "Screen_Up": "%u0634%u0627%u0634%u0629 %u0644%u0644%u0623%u0639%u0644%u0649",
    "Screen_Down": "%u0627%u0644%u0634%u0627%u0634%u0629 %u0644%u0623%u0633%u0641%u0644",
    "Tilt_Left": "%u0627%u0644%u0645%u064A%u0644 %u0627%u0644%u064A%u0633%u0627%u0631",
    "Tilt_Right": "%u062F%u0648%u0631 %u0625%u0644%u0649 %u0627%u0644%u064A%u0645%u064A%u0646",
    "Logo_Up": "%u0627%u0644%u0634%u0639%u0627%u0631 %u0644%u0623%u0639%u0644%u0649",
    "Logo_Down": "%u0627%u0644%u0634%u0639%u0627%u0631 %u0625%u0644%u0649 %u0627%u0644%u0623%u0633%u0641%u0644",
    "Shake": "%u0647%u0632%u0647",
    "block_Compass": "%u0628%u0648%u0635%u0644%u0629",
    "": ""
  },
  "Danish Translation": {
    "block_Tri_LED": "Tri-LED (Slot 1) R (Slot 2) % G (Slot 3) % B (Slot 4) %",
    "port": "Indgang",
    "block_LED": "LED (Slot 1) (Slot 2) %",
    "block_Position_Servo": "Positionsservo (Slot 1) (Slot 2) °",
    "block_Rotation_Servo": "Rotationsservo (Slot 1) (Slot 2) %",
    "block_Play_Note": "Spil tone (Slot 1) i (Slot 2) slag",
    "block_Light": "Lys (Slot 1)",
    "block_Distance": "Afstand (Slot 1)",
    "block_Dial": "Ring til (Slot 1)",
    "block_Other": "Andet (Slot 1)",
    "Accelerometer": "Accelerometer",
    "Magnetometer": "Magnetometer",
    "block_LED_Display": "Display",
    "block_Print": "Vis (Slot 1 = Hej)",
    "block_Button": "Knap (Slot 1)",
    "Screen_Up": "Skærm op",
    "Screen_Down": "Skærm ned",
    "Tilt_Left": "Vip til venstre",
    "Tilt_Right": "Vip til højre",
    "Logo_Up": "Logo op",
    "Logo_Down": "Logo ned",
    "Shake": "Ryst",
    "block_Compass": "Kompas",
    "": ""
  },
  "Korean Translation": {
    "block_Tri_LED": "%uC0BC%uC0C9 LED (Slot 1) %uBE68%uAC15 (Slot 2) % %uCD08%uB85D (Slot 3) % %uD30C%uB791 (Slot 4) %",
    "port": "%uD3EC%uD2B8",
    "block_LED": "LED (Slot 1) (Slot 2) %",
    "block_Position_Servo": "%uC704%uCE58 %uC81C%uC5B4 %uC11C%uBCF4 (Slot 1) (Slot 2) °",
    "block_Rotation_Servo": "%uD68C%uC804%uC18D%uB3C4 %uC81C%uC5B4 %uC11C%uBCF4 (Slot 1) (Slot 2) %",
    "block_Play_Note": "(Slot 1) %uBC88 %uC74C%uC744 (Slot 2) %uBC15%uC790%uB85C %uC5F0%uC8FC%uD558%uAE30",
    "block_Light": "%uBE5B %uC13C%uC11C (Slot 1)",
    "block_Distance": "%uAC70%uB9AC %uC13C%uC11C (Slot 1)",
    "block_Dial": "%uAC00%uBCC0 %uC800%uD56D (Slot 1)",
    "block_Other": "%uC18C%uB9AC %uC13C%uC11C (Slot 1)",
    "Accelerometer": "%uB2E4%uB978 %uC13C%uC11C (Slot 1)",
    "Magnetometer": "%uAC00%uC18D%uB3C4 %uC13C%uC11C",
    "block_LED_Display": "%uC790%uAE30%uB825 %uC13C%uC11C",
    "block_Print": "%uBCF4%uC774%uAE30",
    "block_Button": "%uCD9C%uB825 (Slot 1 = %uC548%uB155)",
    "Screen_Up": "%uBC84%uD2BC (Slot 1)",
    "Screen_Down": "%uD654%uBA74 %uD558%uB298 %uBC29%uD5A5",
    "Tilt_Left": "%uD654%uBA74 %uB545 %uBC29%uD5A5",
    "Tilt_Right": "%uC67C%uCABD %uAE30%uC6B8%uC784",
    "Logo_Up": "%uC624%uB978%uCABD %uAE30%uC6B8%uC784",
    "Logo_Down": "%uB85C%uACE0 %uD558%uB298 %uBC29%uD5A5",
    "Shake": "%uB85C%uACE0 %uB545 %uBC29%uD5A5",
    "block_Compass": "%uD754%uB4E4%uB9BC",
    "": "%uB098%uCE68%uBC18 %uC13C%uC11C"
  },
  "Catalan Translation": {
    "block_Tri_LED": "Tri-LED (Slot 1) vermell (Slot 2) % verd (Slot 3) % blau (Slot 4) %",
    "port": "Port",
    "block_LED": "LED (Slot 1) (Slot 2) %",
    "block_Position_Servo": "Servo posicional (Slot 1) (Slot 2) °",
    "block_Rotation_Servo": "Servo rotacional (Slot 1) (Slot 2) %",
    "block_Play_Note": "Toca nota (Slot 1) durant (Slot 2) temps",
    "block_Light": "Llum",
    "block_Distance": "Distància",
    "block_Dial": "Rodeta",
    "block_Other": "Altres",
    "Accelerometer": "Acceleròmetre",
    "Magnetometer": "Magnetòmetre",
    "block_LED_Display": "Pantalla",
    "block_Print": "Escriu (Slot 1 = Hola)",
    "block_Button": "Botó (Slot 1)",
    "Screen_Up": "Pantalla cap per amunt",
    "Screen_Down": "Pantalla cap per avall",
    "Tilt_Left": "Inclinada a l'esquerra",
    "Tilt_Right": "Inclinada a la dreta",
    "Logo_Up": "Logo cap per amunt",
    "Logo_Down": "Logo cap per avall",
    "Shake": "Sacsejada",
    "block_Compass": "Brúixola",
    "": ""
  },
  "Spanish Translation": {
    "block_Tri_LED": "Led tricolor (Slot 1) R (Slot 2) % G (Slot 3) % B (Slot 4) %",
    "port": "Puerto",
    "block_LED": "LED (Slot 1) (Slot 2) %",
    "block_Position_Servo": "Servo de posicion (Slot 1) (Slot 2) °",
    "block_Rotation_Servo": "Servo de rotacion (Slot 1) (Slot 2) %",
    "block_Play_Note": "Emitir un sonido (Slot 1) por (Slot 2) pulsos",
    "block_Light": "Luz (Slot 1)",
    "block_Distance": "Distancia (Slot 1)",
    "block_Dial": "Dial (Slot 1)",
    "block_Other": "Otro (Slot 1)",
    "Accelerometer": "Acelerometro",
    "Magnetometer": "Magnetometro",
    "block_LED_Display": "Monitor",
    "block_Print": "Imprimir (Slot 1 = Hola)",
    "block_Button": "Pulsador (Slot 1)",
    "Screen_Up": "Subir la pantalla",
    "Screen_Down": "Bajar la pantalla",
    "Tilt_Left": "Ladear hacia la izquierda",
    "Tilt_Right": "Ladear hacia la derecha",
    "Logo_Up": "Logo arriba",
    "Logo_Down": "Logo abajo",
    "Shake": "Sacudir",
    "block_Compass": "Brujula",
    "": ""
  },
  "Hebrew Translation": {
    "block_Tri_LED": "%u05DC%u05D3 %u05E9%u05DC%u05D5%u05E9%u05D4 %u05E6%u05D1%u05E2%u05D9%u05DD       %  R      %  G   %   B",
    "port": "%u05D9%u05E6%u05D9%u05D0%u05D4",
    "block_LED": "%u05DC%u05D3   %",
    "block_Position_Servo": "%u05E1%u05E8%u05D5%u05D5 %u05DB%u05D9%u05D5%u05D5%u05DF",
    "block_Rotation_Servo": "%u05E1%u05E8%u05D5%u05D5 %u05E1%u05D9%u05D1%u05D5%u05D1%u05D9%u05DD      %",
    "block_Play_Note": "%u05E0%u05D2%u05DF %u05EA%u05D5     %u05D1%u05DE%u05E9%u05DA     %u05E4%u05E2%u05D9%u05DE%u05D5%u05EA",
    "block_Light": "%u05D0%u05D5%u05E8",
    "block_Distance": "%u05DE%u05E8%u05D7%u05E7   %u05E1%u05D9%u05D9%u05DE/ %u05DE%u05E8%u05D7%u05E7 %u05D0%u05D9%u05E0%u05E5",
    "block_Dial": "%u05D7%u05D9%u05D5%u05D2",
    "block_Other": "%u05D0%u05D7%u05E8",
    "Accelerometer": "%u05D7%u05D9%u05D9%u05E9%u05DF %u05EA%u05D0%u05D5%u05E6%u05D4",
    "Magnetometer": "%u05D7%u05D9%u05E9%u05DF %u05DE%u05D2%u05E0%u05D8%u05D9",
    "block_LED_Display": "%u05DE%u05E1%u05DA",
    "block_Print": "%u05D4%u05D3%u05E4%u05E1  (    = %u05E9%u05DC%u05D5%u05DD)",
    "block_Button": "%u05DC%u05D7%u05E6%u05DF",
    "Screen_Up": "%u05DC%u05E2%u05DC%u05D5%u05EA %u05DE%u05E1%u05DA",
    "Screen_Down": "%u05DC%u05D4%u05D5%u05E8%u05D9%u05D3 %u05DE%u05E1%u05DA",
    "Tilt_Left": "%u05D4%u05D8%u05D9%u05D9%u05D4 %u05DC%u05E9%u05DE%u05D0%u05DC",
    "Tilt_Right": "%u05D4%u05D8%u05D9%u05D9%u05D4 %u05DC%u05D9%u05DE%u05D9%u05DF",
    "Logo_Up": "%u05DC%u05D5%u05D2%u05D5 %u05DC%u05DE%u05E2%u05DC%u05D4",
    "Logo_Down": "%u05DC%u05D5%u05D2%u05D5 %u05DC%u05DE%u05D8%u05D4",
    "Shake": "%u05DC%u05E0%u05E2%u05E8",
    "block_Compass": "%u05DE%u05E6%u05E4%u05DF",
    "": ""
  }
}